{
  "meta": {
    "semver": "3.0.0"
  },
  "extensions": [],
  "targets": [
    {
      "isStage": true,
      "name": "Stage",
      "variables": {},
      "lists": {
        "list:results": [
          "results",
          []
        ]
      },
      "broadcasts": {},
      "currentCostume": 0,
      "costumes": [
        {
          "name": "backdrop1",
          "bitmapResolution": 1,
          "dataFormat": "png",
          "assetId": "739b5e2a2435f6e1ec2993791b423146",
          "md5ext": "739b5e2a2435f6e1ec2993791b423146.png",
          "rotationCenterX": 240,
          "rotationCenterY": 180
        }
      ],
      "sounds": [
        {
          "name": "pop",
          "assetId": "83a9787d4cb6f3b7632b4ddfebf74367",
          "dataFormat": "wav",
          "format": "",
          "rate": 11025,
          "sampleCount": 258,
          "md5ext": "83a9787d4cb6f3b7632b4ddfebf74367.wav"
        }
      ],
      "volume": 100,
      "tempo": 60,
      "videoTransparency": 50,
      "videoState": "off",
      "textToSpeechLanguage": null,
      "scripts": [
        [
          {
            "opcode": "event_whenflagclicked"
          },
          {
            "opcode": "data_addtolist",
            "fields": {
              "LIST": [
                "results",
                "list:results"
              ]
            },
            "inputs": {
              "ITEM": [
                1,
                [
                  10,
                  "stage"
                ]
              ]
            }
          }
        ]
      ]
    },
    {
      "isStage": false,
      "name": "Sprite1",
      "variables": {},
      "lists": {},
      "broadcasts": {},
      "currentCostume": 0,
      "costumes": [
        {
          "name": "costume1",
          "bitmapResolution": 2,
          "dataFormat": "png",
          "assetId": "d36f6603ec293d2c2198d3ea05109fe0",
          "md5ext": "d36f6603ec293d2c2198d3ea05109fe0.png",
          "rotationCenterX": 0,
          "rotationCenterY": 0
        }
      ],
      "sounds": [
        {
          "name": "pop",
          "assetId": "83a9787d4cb6f3b7632b4ddfebf74367",
          "dataFormat": "wav",
          "format": "",
          "rate": 11025,
          "sampleCount": 258,
          "md5ext": "83a9787d4cb6f3b7632b4ddfebf74367.wav"
        }
      ],
      "volume": 100,
      "visible": true,
      "x": 54,
      "y": 19,
      "size": 100,
      "direction": 90,
      "draggable": false,
      "rotationStyle": "all around",
      "scripts": [
        [
          {
            "opcode": "event_whenflagclicked"
          },
          {
            "opcode": "data_addtolist",
            "fields": {
              "LIST": [
                "results",
                "list:results"
              ]
            },
            "inputs": {
              "ITEM": [
                1,
                [
                  10,
                  "1"
                ]
              ]
            }
          }
        ]
      ]
    },
    {
      "isStage": false,
      "name": "Sprite2",
      "variables": {},
      "lists": {},
      "broadcasts": {},
      "currentCostume": 0,
      "costumes": [
        {
          "name": "costume1",
          "bitmapResolution": 2,
          "dataFormat": "png",
          "assetId": "d36f6603ec293d2c2198d3ea05109fe0",
          "md5ext": "d36f6603ec293d2c2198d3ea05109fe0.png",
          "rotationCenterX": 0,
          "rotationCenterY": 0
        }
      ],
      "sounds": [
        {
          "name": "pop",
          "assetId": "83a9787d4cb6f3b7632b4ddfebf74367",
          "dataFormat": "wav",
          "format": "",
          "rate": 11025,
          "sampleCount": 258,
          "md5ext": "83a9787d4cb6f3b7632b4ddfebf74367.wav"
        }
      ],
      "volume": 100,
      "visible": true,
      "x": -15,
      "y": -35,
      "size": 100,
      "direction": 90,
      "draggable": false,
      "rotationStyle": "all around",
      "scripts": [
        [
          {
            "opcode": "event_whenflagclicked"
          },
          {
            "opcode": "data_addtolist",
            "fields": {
              "LIST": [
                "results",
                "list:results"
              ]
            },
            "inputs": {
              "ITEM": [
                1,
                [
                  10,
                  "2"
                ]
              ]
            }
          }
        ]
      ]
    },
    {
      "isStage": false,
      "name": "Sprite3",
      "variables": {},
      "lists": {},
      "broadcasts": {},
      "currentCostume": 0,
      "costumes": [
        {
          "name": "costume1",
          "bitmapResolution": 2,
          "dataFormat": "png",
          "assetId": "d36f6603ec293d2c2198d3ea05109fe0",
          "md5ext": "d36f6603ec293d2c2198d3ea05109fe0.png",
          "rotationCenterX": 0,
          "rotationCenterY": 0
        }
      ],
      "sounds": [
        {
          "name": "pop",
          "assetId": "83a9787d4cb6f3b7632b4ddfebf74367",
          "dataFormat": "wav",
          "format": "",
          "rate": 11025,
          "sampleCount": 258,
          "md5ext": "83a9787d4cb6f3b7632b4ddfebf74367.wav"
        }
      ],
      "volume": 100,
      "visible": true,
      "x": -84,
      "y": 46,
      "size": 100,
      "direction": 90,
      "draggable": false,
      "rotationStyle": "all around",
      "scripts": [
        [
          {
            "opcode": "event_whenflagclicked"
          },
          {
            "opcode": "data_addtolist",
            "fields": {
              "LIST": [
                "results",
                "list:results"
              ]
            },
            "inputs": {
              "ITEM": [
                1,
                [
                  10,
                  "3"
                ]
              ]
            }
          }
        ]
      ]
    }
  ],
  "monitors": [
    {
      "id": "_data_listcontents_{\"LIST\":\"results\"}",
      "mode": "list",
      "opcode": "data_listcontents",
      "params": {
        "LIST": "results"
      },
      "spriteName": null,
      "value": "",
      "width": 104,
      "height": 204,
      "x": 5,
      "y": 5,
      "visible": false
    }
  ]
}
